informatyka/__init__.py
informatyka/algorytm.py
informatyka/lists.py
informatyka/math.py
informatyka/notice.py
informatyka-0.1.0.dist-info/LICENSE
informatyka-0.1.0.dist-info/METADATA
informatyka-0.1.0.dist-info/WHEEL
informatyka-0.1.0.dist-info/top_level.txt
informatyka-0.1.0.dist-info/RECORD
