Metadata-Version: 2.1
Name: informatyka
Version: 0.1.0
Summary: Biblioteka do zmiennych
Author-email: Mocusiek <testomail123321@gmail.com>
Project-URL: Homepage, https://github.com/pypa/sampleproject
Project-URL: Bug Tracker, https://github.com/pypa/sampleproject/issues
Classifier: Programming Language :: Python :: 3
Classifier: License :: OSI Approved :: MIT License
Classifier: Operating System :: OS Independent
Requires-Python: >=3.9
License-File: LICENSE
